transformer_engine/__init__.py
transformer_engine/common/__init__.py
transformer_engine/common/utils.py
transformer_engine/common/include/transformer_engine/activation.h
transformer_engine/common/include/transformer_engine/cast.h
transformer_engine/common/include/transformer_engine/cast_transpose_noop.h
transformer_engine/common/include/transformer_engine/comm_gemm.h
transformer_engine/common/include/transformer_engine/comm_gemm_overlap.h
transformer_engine/common/include/transformer_engine/cudnn.h
transformer_engine/common/include/transformer_engine/dropout.h
transformer_engine/common/include/transformer_engine/fused_attn.h
transformer_engine/common/include/transformer_engine/fused_rope.h
transformer_engine/common/include/transformer_engine/fused_router.h
transformer_engine/common/include/transformer_engine/gemm.h
transformer_engine/common/include/transformer_engine/hadamard_transform.h
transformer_engine/common/include/transformer_engine/multi_stream.h
transformer_engine/common/include/transformer_engine/multi_tensor.h
transformer_engine/common/include/transformer_engine/normalization.h
transformer_engine/common/include/transformer_engine/padding.h
transformer_engine/common/include/transformer_engine/permutation.h
transformer_engine/common/include/transformer_engine/recipe.h
transformer_engine/common/include/transformer_engine/softmax.h
transformer_engine/common/include/transformer_engine/swizzle.h
transformer_engine/common/include/transformer_engine/transformer_engine.h
transformer_engine/common/include/transformer_engine/transpose.h
transformer_engine/common/recipe/__init__.py
transformer_engine/debug/__init__.py
transformer_engine/debug/features/__init__.py
transformer_engine/debug/features/_test_dummy_feature.py
transformer_engine/debug/features/api.py
transformer_engine/debug/features/disable_fp8_gemm.py
transformer_engine/debug/features/disable_fp8_layer.py
transformer_engine/debug/features/fake_quant.py
transformer_engine_cu13-2.9.0.dist-info/licenses/LICENSE
transformer_engine_cu13-2.9.0.dist-info/METADATA
transformer_engine_cu13-2.9.0.dist-info/WHEEL
transformer_engine_cu13-2.9.0.dist-info/top_level.txt
transformer_engine_cu13-2.9.0.dist-info/RECORD
