Metadata-Version: 2.4
Name: transformer_engine_cu13
Version: 2.9.0
Summary: Transformer acceleration library
Classifier: Programming Language :: Python :: 3
Requires-Python: >=3.10.0
License-File: LICENSE
Requires-Dist: importlib-metadata>=1.0
Requires-Dist: pydantic
Requires-Dist: packaging
Provides-Extra: test
Requires-Dist: pytest>=8.2.1; extra == "test"
Dynamic: classifier
Dynamic: description
Dynamic: description-content-type
Dynamic: license-file
Dynamic: provides-extra
Dynamic: requires-dist
Dynamic: requires-python
Dynamic: summary
